mnisq/__init__.py
mnisq/config/__init__.py
mnisq/fashion_mnist/__init__.py
mnisq/fashion_mnist/loader.py
mnisq/internal/__init__.py
mnisq/internal/dataset/__init__.py
mnisq/internal/dataset/dataset.py
mnisq/internal/generator/__init__.py
mnisq/internal/generator/aqce/AQCE.cpp
mnisq/internal/generator/aqce/AQCE_from_program.py
mnisq/internal/generator/aqce/AQCE_from_python.py
mnisq/internal/generator/aqce/__init__.py
mnisq/internal/generator/cifar_10/__init__.py
mnisq/internal/generator/cifar_10/downloader.py
mnisq/internal/generator/cifar_10/gray_scale.py
mnisq/internal/generator/cifar_10/main.py
mnisq/internal/generator/mnist_like/Source.py
mnisq/internal/generator/mnist_like/__init__.py
mnisq/internal/generator/mnist_like/downloader/__init__.py
mnisq/internal/generator/mnist_like/downloader/mnist.py
mnisq/internal/generator/mnist_like/qasm_converter.py
mnisq/internal/loader/__init__.py
mnisq/internal/loader/mnist_like/__init__.py
mnisq/internal/loader/mnist_like/load.py
mnisq/kuzushiji_mnist/__init__.py
mnisq/kuzushiji_mnist/loader.py
mnisq/mnist/__init__.py
mnisq/mnist/loader.py
mnisq-0.2.0.dist-info/LICENSE
mnisq-0.2.0.dist-info/METADATA
mnisq-0.2.0.dist-info/WHEEL
mnisq-0.2.0.dist-info/RECORD
